ncbi_asm_summary/__init__.py
ncbi_asm_summary/downloader.py
ncbi_asm_summary/parser.py
ncbi_asm_summary/reader.py
ncbi_asm_summary-0.2.4.dist-info/licenses/LICENSE.md
ncbi_asm_summary-0.2.4.dist-info/METADATA
ncbi_asm_summary-0.2.4.dist-info/WHEEL
ncbi_asm_summary-0.2.4.dist-info/entry_points.txt
ncbi_asm_summary-0.2.4.dist-info/top_level.txt
ncbi_asm_summary-0.2.4.dist-info/RECORD
