Metadata-Version: 2.4
Name: ncbi_asm_summary
Version: 0.2.4
Author-email: "Chase M. Clark" <chase@chasingmicrobes.com>
License: MIT
Project-URL: repository, https://github.com/evoquant/ncbi_asm_summary
Classifier: Development Status :: 3 - Alpha
Classifier: Intended Audience :: Science/Research
Classifier: License :: OSI Approved :: MIT License
Classifier: Operating System :: Unix
Classifier: Operating System :: POSIX
Classifier: Operating System :: Microsoft :: Windows
Classifier: Operating System :: OS Independent
Classifier: Topic :: Software Development :: Libraries :: Python Modules
Classifier: License :: OSI Approved :: MIT License
Classifier: Programming Language :: Python :: 3
Requires-Python: >=3.12
License-File: LICENSE.md
Requires-Dist: tqdm
Requires-Dist: requests
Provides-Extra: ci
Requires-Dist: pytest-cov; extra == "ci"
Provides-Extra: cd
Requires-Dist: twine; extra == "cd"
Dynamic: license-file
